sangarak/__init__.py
sangarak/sangarak.py
sangarak/tests/__init__.py
sangarak-0.1.dist-info/METADATA
sangarak-0.1.dist-info/RECORD
sangarak-0.1.dist-info/WHEEL
sangarak-0.1.dist-info/top_level.txt
