Metadata-Version: 2.1
Name: sangarak
Version: 0.1
Summary: Python library for reading matrices from many files and generating a single numpy matrix
Home-page: https://github.com/rioyokotalab/sangarak
Author: Sameer Deshmukh
Author-email: sameer.desmukh93@gmail.com
License: BSD 3-clause
Keywords: numpy,mpi,matrix
Platform: UNKNOWN
Classifier: Programming Language :: Python :: 3
Classifier: License :: OSI Approved :: BSD License
Classifier: Operating System :: OS Independent
Requires-Dist: numpy
